dictlist2/__init__.py
dictlist2/_version.py
dictlist2-1.0.3.dist-info/licenses/LICENSE
dictlist2-1.0.3.dist-info/METADATA
dictlist2-1.0.3.dist-info/WHEEL
dictlist2-1.0.3.dist-info/top_level.txt
dictlist2-1.0.3.dist-info/RECORD
