Metadata-Version: 2.4
Name: DictList2
Version: 1.0.3
Summary: It is a lightweight Python library that extends the built-in list for convenient work with arrays of dictionaries.
Author-email: Sergey Strukov <strukovsv@main.ru>
Project-URL: Homepage, https://github.com/strukovsv/dictlist2
Project-URL: Issues, https://github.com/strukovsv/dictlist2/issues
Classifier: Development Status :: 4 - Beta
Classifier: Intended Audience :: Developers
Classifier: Topic :: Software Development :: Build Tools
Classifier: License :: OSI Approved :: MIT License
Classifier: Programming Language :: Python :: 3.11
Requires-Python: >=3.11
License-File: LICENSE
Dynamic: license-file
